{
  "title": "Μεθοδολογία Αθλητικής Έρευνας",
  "id": "5497e781-5dae-41eb-9b90-c93773a1b7da",
  "questions": [
    {
      "id": "d64fb01f-0a8c-4f6c-b258-d47926c87ffe",
      "text": "1) Ο μέσος όρος των μετρήσεων 7, 13, 10 είναι:",
      "options": [
        {
          "id": "76aee2c0-c41a-41be-ae00-13d6678a9843",
          "text": "10",
          "isCorrect": true
        },
        {
          "id": "6dc01912-e71d-4dc8-a6bc-7e23496b2eed",
          "text": "90",
          "isCorrect": false
        },
        {
          "id": "ea6ee89e-ef71-4a82-9f14-2f4681fa5005",
          "text": "30",
          "isCorrect": false
        },
        {
          "id": "9e6b9210-ab41-481d-92e2-2d5319ae2c6c",
          "text": "20",
          "isCorrect": false
        }
      ]
    },
    {
      "id": "21bc979c-0b1e-425a-ac60-dd865a5d4438",
      "text": "2) Στο κεφάλαιο της εισαγωγής περιγράφω:",
      "options": [
        {
          "id": "ad74f014-5fe1-4124-9e18-3b6986dc349f",
          "text": "Όλη την πληροφορία που έχω",
          "isCorrect": true
        },
        {
          "id": "a6521e9a-1450-43e0-ac98-87a32696418c",
          "text": "Τα αποτελέσματα της μελέτης μου",
          "isCorrect": false
        },
        {
          "id": "135f1b76-15d7-48d4-af7a-ba1c2a491e02",
          "text": "Τα αποτελέσματα των άλλων",
          "isCorrect": false
        },
        {
          "id": "e697da31-db36-4b99-9c80-ded333e62262",
          "text": "Τους περιορισμούς",
          "isCorrect": false
        }
      ]
    },
    {
      "id": "9bc54ffb-6282-46b2-bdd8-80a74401c834",
      "text": "3) Στην ανασκόπηση της βιβλιογραφίας",
      "options": [
        {
          "id": "22cce69c-b9f4-409f-8583-73cc55643d7d",
          "text": "Αρχειοθετώ",
          "isCorrect": false
        },
        {
          "id": "07249935-5d5f-4762-aeb5-cff7382a6ad0",
          "text": "Αναζητώ, αρχειοθετώ, αξιολογώ, διαβάζω",
          "isCorrect": true
        },
        {
          "id": "aacd9293-6172-43dc-927d-53c14381a009",
          "text": "Αναζητώ, αρχειοθετώ",
          "isCorrect": false
        },
        {
          "id": "62526848-bae0-48d5-8079-884b2571a66b",
          "text": "Αξιολογώ, διαβάζω",
          "isCorrect": false
        }
      ]
    },
    {
      "id": "25407cf9-cb23-49fd-9f08-3e17c6af8fbe",
      "text": "4) Τα εξεταζόμενα άτομα είναι:",
      "options": [
        {
          "id": "59ffd5be-4bd9-4b2c-915c-0c94a824fffa",
          "text": "Οι συμμετέχοντες όλων των εργασιών που αναφέρονται στη μελέτη",
          "isCorrect": false
        },
        {
          "id": "6e19a592-9ab7-44b8-a360-ad9a66ca97ba",
          "text": "Οι συγγραφείς",
          "isCorrect": false
        },
        {
          "id": "80b0d3a6-7006-43fd-a181-0e54c7d438cd",
          "text": "Οι συμμετέχοντες της μελέτης",
          "isCorrect": true
        },
        {
          "id": "0231fc57-ccaa-4ad2-a619-e2fd9681e6eb",
          "text": "Οι γονείς",
          "isCorrect": false
        }
      ]
    },
    {
      "id": "2000ad3a-7bc3-42b5-92d8-038ef0b11fac",
      "text": "5) Τι περιέχει το δείγμα μιας μελέτης;",
      "options": [
        {
          "id": "c207b544-5483-40a7-a5ed-382d1dccd82d",
          "text": "Όλους τους συμμετέχοντες",
          "isCorrect": true
        },
        {
          "id": "2443041f-2c83-4da3-9726-90b411ff7f8b",
          "text": "Επιλογή μερικών ατόμων από τα εξεταζόμενα",
          "isCorrect": false
        },
        {
          "id": "0ec4f426-5b1a-4ce8-af69-3ee2439f2d6c",
          "text": "Αυτούς με τις πιο ακραίες τιμές",
          "isCorrect": false
        },
        {
          "id": "b489e2db-2120-4793-83ef-09afc2a46b47",
          "text": "Αυτούς με τις χειρότερες τιμές",
          "isCorrect": false
        }
      ]
    },
    {
      "id": "af8d0301-d584-4aae-9ff6-d639f4bd4301",
      "text": "6) Μπορούν τα παιδιά να κάνουν προπόνηση αντιστάσεων;",
      "options": [
        {
          "id": "0c850241-fb68-4246-8ccd-75b2b1718642",
          "text": "Μετά τα 18",
          "isCorrect": false
        },
        {
          "id": "82cf662b-5a42-4273-88e1-c7009e047815",
          "text": "Ναι",
          "isCorrect": true
        },
        {
          "id": "e846eba5-0efc-4102-9328-85633b74fefe",
          "text": "Εξαρτάται",
          "isCorrect": false
        },
        {
          "id": "43b4d618-733b-4b5f-94fc-6612cea76552",
          "text": "Ποτέ",
          "isCorrect": false
        }
      ]
    },
    {
      "id": "565bcfbc-2da0-4e81-814b-61b90aa122af",
      "text": "7) Με πόσες επαναλήψεις επιτυγχάνουμε αλλαγές στην δύναμη;",
      "options": [
        {
          "id": "5591cf5a-952d-47aa-ad11-d0bfbc99f6bc",
          "text": "1-6",
          "isCorrect": true
        },
        {
          "id": "04d73bc2-2ffc-4a27-b7ba-7020ea2984cd",
          "text": "8-12",
          "isCorrect": false
        },
        {
          "id": "06ba58c8-f124-48c9-aa38-4ce4b87f1bf8",
          "text": "15-20",
          "isCorrect": false
        },
        {
          "id": "f93fbe0b-bd7d-4a91-9130-cfef86fdbf5a",
          "text": "Μέχρι εξάντλησης",
          "isCorrect": false
        }
      ]
    },
    {
      "id": "7cba8284-ff74-4553-bafa-a7e4f757e186",
      "text": "8) Η μεθοδολογία της έρευνας είναι:",
      "options": [
        {
          "id": "135205c9-552a-45bc-96f3-31dd86bc6963",
          "text": "Επιστήμη",
          "isCorrect": true
        },
        {
          "id": "4f618a00-e1fd-48df-98b5-e3d06bdda980",
          "text": "Πειράματα",
          "isCorrect": false
        },
        {
          "id": "185e56e1-cbe7-4ae1-80b1-cfb3cc0c2475",
          "text": "Συνθήκες",
          "isCorrect": false
        },
        {
          "id": "02e09cc0-141f-403e-8902-732a12ee6dfb",
          "text": "Ενέργειες",
          "isCorrect": false
        }
      ]
    },
    {
      "id": "09c68be1-5485-4875-a4ad-11b6e367cac5",
      "text": "9) Η ερευνητική διαδικασία είναι:",
      "options": [
        {
          "id": "31db1cdb-af4d-445e-97a3-4d6c103e20a2",
          "text": "Όλες οι απαντήσεις είναι σωστές",
          "isCorrect": true
        },
        {
          "id": "5a60dc1d-dff3-401f-b786-644abd4440b1",
          "text": "Προβληματισμός",
          "isCorrect": false
        },
        {
          "id": "0e5203ad-826b-4a3b-b1d3-b0911cd2fdfd",
          "text": "Σχέδιο – αξιοπιστία μετρήσεων",
          "isCorrect": false
        },
        {
          "id": "39bdb7e4-c29b-4828-a27d-131bd7469713",
          "text": "Ανάλυση / επαλήθευση / επικύρωση δεδομένων",
          "isCorrect": false
        }
      ]
    },
    {
      "id": "bd36532a-22b0-4bb4-a07d-6333839856cc",
      "text": "10) Στη συζήτηση προσπαθώ:",
      "options": [
        {
          "id": "7c824132-2cbf-427b-83e0-472229b83579",
          "text": "Όλες οι απαντήσεις είναι σωστές",
          "isCorrect": true
        },
        {
          "id": "31d996ea-ff04-4f72-9d16-ed1e279943e9",
          "text": "Να κάνω κριτική αποτελεσμάτων",
          "isCorrect": false
        },
        {
          "id": "7c7efa4b-753e-4bf2-921c-82071342daf0",
          "text": "Να αναφέρω περιορισμούς",
          "isCorrect": false
        },
        {
          "id": "f3327637-a9dd-4c3d-8919-0f405a17262f",
          "text": "Να προτείνω νέες απόψεις",
          "isCorrect": false
        }
      ]
    },
    {
      "id": "fbd0010c-2e0b-4273-9d05-3938b74d5392",
      "text": "11) Πόσες λέξεις κλειδιά χρειάζομαι;",
      "options": [
        {
          "id": "106341f9-9c65-4f4f-8633-e191f080329e",
          "text": "Οκτώ",
          "isCorrect": false
        },
        {
          "id": "c0cd1d49-7a36-4c41-9ad8-40a291ca9188",
          "text": "Τρείς έως πέντε",
          "isCorrect": true
        },
        {
          "id": "bda802b7-d957-421f-8728-06009d09a313",
          "text": "Τις κυριότερες του τίτλου",
          "isCorrect": false
        },
        {
          "id": "ee023fe0-76db-483c-a614-86b320f8c612",
          "text": "Τρείς",
          "isCorrect": false
        }
      ]
    },
    {
      "id": "86822c6e-cdbc-44c1-a5e5-cd183f0d5079",
      "text": "12) Η βιβλιογραφία περιέχει:",
      "options": [
        {
          "id": "5d1d8fd3-c5af-4fda-90b1-2b8ab12930fd",
          "text": "Πληροφορίες από επιστημονικά βιβλία",
          "isCorrect": false
        },
        {
          "id": "b47003cc-c33a-4f54-83d6-7a5a3a95c2da",
          "text": "Όλες οι απαντήσεις είναι σωστές",
          "isCorrect": true
        },
        {
          "id": "c93d7ebc-9fae-43ea-8c7c-d87558087643",
          "text": "Απόψεις επιστημόνων σε συνέδρια",
          "isCorrect": false
        },
        {
          "id": "5ec1e7b4-87a2-49b1-9d1b-60f1e0e72130",
          "text": "Άρθρα ερευνητικών περιοδικών",
          "isCorrect": false
        }
      ]
    },
    {
      "id": "4833778e-2d6c-468e-986f-ddc1868d02c7",
      "text": "13) Η μεθοδολογία της μελέτης αφορούσε:",
      "options": [
        {
          "id": "a77fe4c5-ca3e-4fcb-9177-36baed846328",
          "text": "Στην άδεια διεξαγωγής",
          "isCorrect": false
        },
        {
          "id": "f0edf32b-7f2d-4fd7-a549-1cd628c1c35f",
          "text": "Στο δείγμα",
          "isCorrect": false
        },
        {
          "id": "77ae1ab3-e14b-44fd-9503-5018a2efb71b",
          "text": "Όλες οι απαντήσεις είναι σωστές",
          "isCorrect": true
        },
        {
          "id": "a59b1eea-750d-4b65-b6f1-62ee2a37735f",
          "text": "Στην διαδικασία του πειράματος",
          "isCorrect": false
        }
      ]
    },
    {
      "id": "46665a15-bf89-44bc-8ce7-d35146284185",
      "text": "14) Τι σημαίνουν οι αστερίσκοι σε έναν πίνακα;",
      "options": [
        {
          "id": "d2096cb7-c473-4f7f-b499-875ac1a3cec7",
          "text": "Σπουδαιότητα",
          "isCorrect": false
        },
        {
          "id": "a50bd747-46cc-4df6-afaa-5f60c51852c7",
          "text": "Στατιστική σημαντικότητα",
          "isCorrect": true
        },
        {
          "id": "491b8e64-ab29-4954-a414-3f3cdab65121",
          "text": "Τις ζώνες των αθλητών",
          "isCorrect": false
        },
        {
          "id": "5081d3ff-308a-4da0-9855-bb14e51244c8",
          "text": "Δεύτερη ερμηνεία",
          "isCorrect": false
        }
      ]
    },
    {
      "id": "4b7cf79e-37e7-44f9-b0c2-62f0353c32eb",
      "text": "15) Ο πίνακας 1 μας δείχνει:",
      "options": [
        {
          "id": "3802fe58-edc5-4796-9e81-630cb42e15e8",
          "text": "Τις διαφορές στην πειραματική ομάδα",
          "isCorrect": false
        },
        {
          "id": "4fd3d3ca-8cf2-444e-992e-7a9f750941d7",
          "text": "Τις διαφορές σε διάφορους παραμέτρους",
          "isCorrect": false
        },
        {
          "id": "86612b0d-2dba-4741-b4a6-93595e4a68a7",
          "text": "Όλες οι απαντήσεις είναι σωστές",
          "isCorrect": true
        },
        {
          "id": "c37df564-ba41-47e6-9bc0-1e440c6928d7",
          "text": "Τις διαφορές στην ομάδα ελέγχου",
          "isCorrect": false
        }
      ]
    },
    {
      "id": "eb365a97-1957-4ee9-90a1-c04445ae8f77",
      "text": "16) Τι σημαίνει ποσοστιαία διαφορά:",
      "options": [
        {
          "id": "3a626740-1fb2-4ca8-ae35-22c2c174354d",
          "text": "Η αύξηση επί της 100",
          "isCorrect": false
        },
        {
          "id": "85972885-6e74-44c3-81c7-585be99a69ee",
          "text": "Η μείωση επί της 100",
          "isCorrect": false
        },
        {
          "id": "9cae4185-aecd-4100-99cd-5b0cafc947df",
          "text": "Η έλλειψη διαφορών επί της 100",
          "isCorrect": false
        },
        {
          "id": "5697c914-f3ac-4f7d-9361-078a6d94fd51",
          "text": "Η διαφορά επί της 100",
          "isCorrect": true
        }
      ]
    },
    {
      "id": "57c2cdc9-b6eb-46e6-b703-8cc6dcd9d57f",
      "text": "17) Ένας πίνακας πρέπει να είναι:",
      "options": [
        {
          "id": "add9ed6d-0d4e-4d82-a791-96b71da04f2f",
          "text": "Κατανοητός",
          "isCorrect": false
        },
        {
          "id": "37b720a8-2af2-4a64-a347-3f4c0edd0354",
          "text": "Πληροφοριακός",
          "isCorrect": false
        },
        {
          "id": "2ae80ca7-4544-4e07-b0e9-4ed43a93cb17",
          "text": "Όλες οι απαντήσεις είναι σωστές",
          "isCorrect": true
        },
        {
          "id": "d69d8b56-abda-4ea6-b62d-5c8ace380cec",
          "text": "Σύντομος",
          "isCorrect": false
        }
      ]
    },
    {
      "id": "21c2ee2f-8ec0-4d31-a6c8-c63e838fcbe3",
      "text": "18) Τι σημαίνει ο αριθμός μετά από μια συγγραφική ομάδα;",
      "options": [
        {
          "id": "93a3732e-b921-4663-b628-879fa5ba390d",
          "text": "Το σύνολο των εργασιών της ομάδας",
          "isCorrect": false
        },
        {
          "id": "9692d6c7-8c4e-42b9-a40a-f0ecfa776d65",
          "text": "Οι αναδημοσιεύσεις του άρθρου",
          "isCorrect": false
        },
        {
          "id": "9d8efe89-ae8e-4106-bd06-6093f8d1d9b5",
          "text": "Ο αριθμός της παραπομπής",
          "isCorrect": true
        },
        {
          "id": "d143ff7b-a755-4a25-83ef-ad4572af40a3",
          "text": "Πόσοι ήταν τα εξεταζόμενα άτομα",
          "isCorrect": false
        }
      ]
    },
    {
      "id": "3deee972-47a2-44fc-8033-ac5708ac00c8",
      "text": "19) Πόσα άρθρα φτάνουν για μια διπλωματική εργασία;",
      "options": [
        {
          "id": "89d40d01-463c-47a4-bf0d-6dfc97ad71f5",
          "text": "2–3",
          "isCorrect": false
        },
        {
          "id": "d1e92377-a8b8-4054-85b6-7ef5eaa29302",
          "text": "Όσα απαιτούνται για την επιστημονική παρουσίαση σύμφωνα με τις αρχές της μεθολογίας της έρευνας",
          "isCorrect": true
        },
        {
          "id": "2549903e-72f9-4be6-81f9-5976c4bc016a",
          "text": "20",
          "isCorrect": false
        },
        {
          "id": "9faa9cff-eb44-4669-8568-977f7d2b13f9",
          "text": "80",
          "isCorrect": false
        }
      ]
    },
    {
      "id": "f4a45e25-cd67-4596-b7e7-77c3e00333ff",
      "text": "20) Πλαγιαρισμός – λογοκλοπή:",
      "options": [
        {
          "id": "077e01d4-df3a-4d17-b63c-d578c67879cb",
          "text": "Η χρήση της βιβλιογραφίας μιας μελέτης",
          "isCorrect": false
        },
        {
          "id": "dedf1481-f93f-4831-b974-912ffb9e708f",
          "text": "Η οικοιοποίηση λόγων και ιδεών",
          "isCorrect": true
        },
        {
          "id": "da5c7032-c6b4-4965-a077-4a2c5b0f751d",
          "text": "Η αναφορά μιας μελέτης",
          "isCorrect": false
        },
        {
          "id": "ed514a89-af60-42ed-a5e8-30a9ce0de78c",
          "text": "Η αντιγραφή της δομής μιας μελέτης",
          "isCorrect": false
        }
      ]
    },
    {
      "id": "da5f1809-6d59-4542-a6f3-a7792ba0dad9",
      "text": "21) Η μέση τιμή είναι:",
      "options": [
        {
          "id": "09fc94f9-0c8e-4c00-ae73-6e60884fe876",
          "text": "Η καλή κατανομή του δείγματος",
          "isCorrect": false
        },
        {
          "id": "b0418924-7e71-4565-b233-ed2304ffe44b",
          "text": "Το άθροισμα των τιμών δια του αριθμού των αριθμών συλλογής",
          "isCorrect": true
        },
        {
          "id": "566ce621-902f-4cb6-ad2a-aa97b1a6a327",
          "text": "Η τυπική απόκλιση των τιμών",
          "isCorrect": false
        },
        {
          "id": "4768fbca-8e5e-4b58-be8d-dbd75b86792b",
          "text": "Το εύρος των τιμών των δεδομένων",
          "isCorrect": false
        }
      ]
    },
    {
      "id": "9e7ac677-d8c6-496f-9271-a8ac4d5a79c3",
      "text": "22) Χρησιμοποιώ φωτογραφίες;",
      "options": [
        {
          "id": "9bbdad82-f5ee-4bc4-b6f0-14661a97befe",
          "text": "Από ερευνητικά περιοδικά",
          "isCorrect": false
        },
        {
          "id": "6e7f9f53-6b87-4b28-ac60-483124fe4c80",
          "text": "Μετά από άδεια του δημιουργού",
          "isCorrect": true
        },
        {
          "id": "f0f085ac-776f-4993-9731-23c1007056b8",
          "text": "Ποτέ",
          "isCorrect": false
        },
        {
          "id": "6bc55f20-ac6b-430b-96ef-a6403bcdda08",
          "text": "Από το διαδίκτυο",
          "isCorrect": false
        }
      ]
    },
    {
      "id": "cb7798ea-1494-4ec2-8cae-bc64a8e81579",
      "text": "23) Πόσα άτομα θεωρούνται επαρκή για την ολοκλήρωση μιας μελέτης;",
      "options": [
        {
          "id": "c982e844-a793-4eb2-a62a-a91a93c075d4",
          "text": "Όσα υποδεικνύονται από τον έλεγχο ισχύος της μελέτης",
          "isCorrect": true
        },
        {
          "id": "48bb4e00-b5ea-452c-840a-097968270b81",
          "text": "Όσα απαιτούνται για να επιβεβαιώσω το σκοπό",
          "isCorrect": false
        },
        {
          "id": "9b97acfb-ae6c-46da-b5db-2ef173f9b75e",
          "text": "10",
          "isCorrect": false
        },
        {
          "id": "1741f9e5-5c23-4d14-8ffe-851d56f176ae",
          "text": "7",
          "isCorrect": false
        }
      ]
    },
    {
      "id": "b365099c-383f-404f-bc5a-224576af7b2a",
      "text": "24) Πλαγιαρισμός:",
      "options": [
        {
          "id": "34ce200b-1346-4e7d-a2e8-41ca0dfd91f0",
          "text": "Επιτρέπεται κατόπιν αδείας από το περιοδικό",
          "isCorrect": false
        },
        {
          "id": "b26258cb-8f5f-4d20-9aa8-0b0987c274ba",
          "text": "Επιτρέπεται",
          "isCorrect": false
        },
        {
          "id": "b9dc15ea-a6a7-4c99-92ef-3c293b451ab1",
          "text": "Επιτρέπεται υπό συνθήκες",
          "isCorrect": false
        },
        {
          "id": "52ac6bee-bdbc-48bf-a391-c9be7d10bd33",
          "text": "Απαγορεύεται – τιμωρείται",
          "isCorrect": true
        }
      ]
    }
  ]
}